mzrt2h5/__init__.py
mzrt2h5/cli.py
mzrt2h5/dataset.py
mzrt2h5/processing.py
mzrt2h5/simulation.py
mzrt2h5/visualization.py
mzrt2h5/mzrtsim/__init__.py
mzrt2h5/mzrtsim/mzm_default.txt
mzrt2h5/mzrtsim/parser.py
mzrt2h5/mzrtsim/reader.py
mzrt2h5/mzrtsim/sim.py
mzrt2h5/mzrtsim/writer.py
mzrt2h5/mzrtsim/data/monahrms1.pkl
mzrt2h5-0.1.7.dist-info/licenses/LICENSE
mzrt2h5-0.1.7.dist-info/METADATA
mzrt2h5-0.1.7.dist-info/WHEEL
mzrt2h5-0.1.7.dist-info/entry_points.txt
mzrt2h5-0.1.7.dist-info/top_level.txt
mzrt2h5-0.1.7.dist-info/RECORD
