Metadata-Version: 2.4
Name: mzrt2h5
Version: 0.1.7
Summary: A package to convert mzML files to HDF5 for deep learning.
Author-email: Miao Yu <yufreecas@gmail.com>
License: MIT
Project-URL: Homepage, https://github.com/yufree/mzrt2h5
Project-URL: Bug Tracker, https://github.com/yufree/mzrt2h5/issues
Classifier: Programming Language :: Python :: 3
Classifier: License :: OSI Approved :: MIT License
Classifier: Operating System :: OS Independent
Requires-Python: >=3.8
License-File: LICENSE
Requires-Dist: numpy
Requires-Dist: pandas
Requires-Dist: pymzml
Requires-Dist: scipy
Requires-Dist: h5py
Requires-Dist: torch
Requires-Dist: tqdm
Requires-Dist: Flask
Requires-Dist: click
Requires-Dist: matplotlib
Dynamic: license-file
